LICENSE
MANIFEST.in
README.rst
setup.py
Orange_Textable_Prototypes.egg-info/PKG-INFO
Orange_Textable_Prototypes.egg-info/SOURCES.txt
Orange_Textable_Prototypes.egg-info/dependency_links.txt
Orange_Textable_Prototypes.egg-info/entry_points.txt
Orange_Textable_Prototypes.egg-info/not-zip-safe
Orange_Textable_Prototypes.egg-info/requires.txt
Orange_Textable_Prototypes.egg-info/top_level.txt
_textable_prototypes/__init__.py
_textable_prototypes/widgets/OWTextableTheatreClassique.py
_textable_prototypes/widgets/OWWebSearch.py
_textable_prototypes/widgets/__init__.py
_textable_prototypes/widgets/icons/Category-Textable-Prototypes.png
_textable_prototypes/widgets/icons/Theatre_Classique_16.png
_textable_prototypes/widgets/icons/Theatre_Classique_36.png
_textable_prototypes/widgets/icons/Theatre_Classique_48.png
_textable_prototypes/widgets/icons/Theatre_Classique_54.png
_textable_prototypes/widgets/icons/icon_WebSearch_transpa_16.png
_textable_prototypes/widgets/icons/icon_WebSearch_transpa_36.png
_textable_prototypes/widgets/icons/icon_WebSearch_transpa_48.png
_textable_prototypes/widgets/icons/icon_WebSearch_transpa_54.png
docs/Makefile
docs/rst/Thumbs.db
docs/rst/build_the_docs.bat
docs/rst/conf.py
docs/rst/index.rst
docs/rst/theatre_classique.rst
docs/rst/websearch.rst
docs/rst/figures/Theatre_Classique_54.png
docs/rst/figures/Thumbs.db
docs/rst/figures/WebSearch_Bing.png
docs/rst/figures/WebSearch_Twitter.png
docs/rst/figures/WebSearch_Twitter_key.png
docs/rst/figures/WebSearch_Wikipedia.png
docs/rst/figures/banner.jpg
docs/rst/figures/icon_WebSearch_transpa_54.png
docs/rst/figures/theatre_classique_advanced_interface.png
docs/rst/figures/theatre_classique_basic_interface.png
specs/theatre_classique.rst
specs/web_search.rst