Metadata-Version: 1.1
Name: Orange-Textable-Prototypes
Version: 0.1.4
Summary: Extra widgets for the Textable text analysis package.
Home-page: https://github.com/axanthos/TextablePrototypes
Author: University of Lausanne
Author-email: aris.xanthos@unil.ch
License: GPLv3
Download-URL: https://pypi.python.org/pypi/Orange-Textable-Prototypes
Keywords: text mining,text analysis,textable,orange,orange add-on
Platform: UNKNOWN
Classifier: Development Status :: 3 - Alpha
Classifier: License :: OSI Approved :: GNU General Public License v3 (GPLv3)
Classifier: Programming Language :: Python :: 2.6
Classifier: Programming Language :: Python :: 2.7
Classifier: License :: OSI Approved :: GNU General Public License v3 or later (GPLv3+)
Classifier: Operating System :: OS Independent
Classifier: Topic :: Scientific/Engineering :: Information Analysis
Classifier: Topic :: Text Processing :: General
Classifier: Topic :: Text Processing :: Linguistic
Classifier: Topic :: Software Development :: Libraries :: Python Modules
Classifier: Intended Audience :: Education
Classifier: Intended Audience :: Science/Research
Classifier: Intended Audience :: Developers
